[
  {
    "name": "Sahil Lamba",
    "image": "https://ik.imagekit.io/difw0fvlzb/Alum/Sahil_Lamba_DGkA1PyOP.jpg?ik-sdk-version=javascript-1.4.3&updatedAt=1654207445451",
    "position": "SDE",
    "org": "Amazon",
    "facebook": "",
    "linkedin": "https://www.linkedin.com/in/sahillamba/"
  },
  {
    "name": "Aayush Sable",
    "image": "https://ik.imagekit.io/difw0fvlzb/Alum/Aayush_Sable_KCAK7ahn8.jpg?ik-sdk-version=javascript-1.4.3&updatedAt=1654207258193",
    "position": "Sr. Manager Operations",
    "org": "Tata steel Ltd.",
    "facebook": "",
    "linkedin": "https://www.linkedin.com/in/sableaayush/"
  },
  {
    "name": "Hard Matarkar",
    "image": "https://ik.imagekit.io/difw0fvlzb/Alum/Hard_Matarkar_3C1m3vV2pZ.jpg?ik-sdk-version=javascript-1.4.3&updatedAt=1654207257994",
    "position": "Research Assistant IISc Banglore",
    "org": "IISc Banglore",
    "facebook": "",
    "linkedin": "https://www.linkedin.com/in/hard-matarkar-0b1b2610b/"
  },
  {
    "name": "Aakash Parikh",
    "image": "https://ik.imagekit.io/difw0fvlzb/Alum/Aakash_Parikh_nvpp5VR2e.jpg?ik-sdk-version=javascript-1.4.3&updatedAt=1654207257913",
    "position": "Senior Associate",
    "org": "Boston Consulting Group",
    "facebook": "",
    "linkedin": "https://www.linkedin.com/in/aakash-parikh-283065a5/"
  },
  {
    "name": "Aayush Parth",
    "image": "https://ik.imagekit.io/difw0fvlzb/Alum/Aayush_Parth_7bX6BY6vt.jpg?ik-sdk-version=javascript-1.4.3&updatedAt=1654207257242",
    "position": "Sr. Project Manager",
    "org": "P&G",
    "facebook": "",
    "linkedin": "https://www.linkedin.com/in/aayush-parth-78b3027b/"
  },
  {
    "name": "Mihir Rana",
    "image": "https://ik.imagekit.io/difw0fvlzb/Alum/Mihir_Rana_lOPjg4KzP.jpg?ik-sdk-version=javascript-1.4.3&updatedAt=1654207258497",
    "position": "Machine Learning Scientist",
    "org": "Trip Advisor",
    "facebook": "",
    "linkedin": "https://www.linkedin.com/in/ranamihir/"
  },
  {
    "name": "Aman Agasi",
    "image": "https://ik.imagekit.io/difw0fvlzb/Alum/Aman_Agasi_CbiY0Mqj-.jpg?ik-sdk-version=javascript-1.4.3&updatedAt=1654207257223",
    "position": "Product Analyst",
    "org": "Zomato",
    "facebook": "",
    "linkedin": "https://www.linkedin.com/in/amanagasi/"
  }
]
